tracardi_day_night_split/__init__.py
tracardi_day_night_split/plugin.py
tracardi_day_night_split/model/__init__.py
tracardi_day_night_split/model/configuration.py
tracardi_day_night_split/model/__pycache__/__init__.cpython-38.pyc
tracardi_day_night_split/model/__pycache__/configuration.cpython-38.pyc
tracardi_day_night_split/service/__init__.py
tracardi_day_night_split/service/day_night_checker.py
tracardi_day_night_split/service/__pycache__/__init__.cpython-38.pyc
tracardi_day_night_split/service/__pycache__/day_night_checker.cpython-38.pyc
tracardi_day_night_split-0.6.1.dist-info/LICENSE.md
tracardi_day_night_split-0.6.1.dist-info/METADATA
tracardi_day_night_split-0.6.1.dist-info/WHEEL
tracardi_day_night_split-0.6.1.dist-info/top_level.txt
tracardi_day_night_split-0.6.1.dist-info/RECORD
