Metadata-Version: 2.1
Name: tracardi-day-night-split
Version: 0.6.1
Summary: The purpose of this plugin is to split the workflow depending on whether it is day or night of its execution.
Home-page: UNKNOWN
Author: Risto Kowaczewski
Author-email: risto.kowaczewski@gmail.com
License: UNKNOWN
Keywords: tracardi,plugin
Platform: UNKNOWN
Classifier: Programming Language :: Python :: 3
Classifier: License :: OSI Approved :: MIT License
Classifier: Operating System :: OS Independent
Requires-Python: >=3.8
License-File: LICENSE.md
Requires-Dist: pydantic
Requires-Dist: tracardi-plugin-sdk (>=0.6.22)
Requires-Dist: geopy (>=2.2.0)
Requires-Dist: astral (>=2.2)
Requires-Dist: pytz
Requires-Dist: tracardi-dot-notation
